ipython_pygments_lexers.py
ipython_pygments_lexers-1.1.0.dist-info/entry_points.txt
ipython_pygments_lexers-1.1.0.dist-info/WHEEL
ipython_pygments_lexers-1.1.0.dist-info/METADATA
ipython_pygments_lexers-1.1.0.dist-info/RECORD
