Metadata-Version: 2.3
Name: ipython_pygments_lexers
Version: 1.1.0
Summary: Defines a variety of Pygments lexers for highlighting IPython code.
Author-email: The IPython Development Team <ipython-dev@python.org>
Requires-Python: >=3.8
Classifier: Framework :: IPython
Classifier: License :: OSI Approved :: BSD License
Requires-Dist: pygments
Project-URL: Source, https://github.com/ipython/ipython-pygments-lexers
